eg4_inverter_api/__init__.py
eg4_inverter_api/client.py
eg4_inverter_api/constants.py
eg4_inverter_api/exceptions.py
eg4_inverter_api/models.py
eg4_inverter_api-0.1.5.dist-info/LICENSE
eg4_inverter_api-0.1.5.dist-info/METADATA
eg4_inverter_api-0.1.5.dist-info/WHEEL
eg4_inverter_api-0.1.5.dist-info/top_level.txt
eg4_inverter_api-0.1.5.dist-info/RECORD
