Metadata-Version: 2.2
Name: eg4_inverter_api
Version: 0.1.5
Summary: A Python API for interacting with EG4 Inverter systems.
Home-page: https://github.com/twistedroutes/eg4_inverter_api
Author: Garreth Jeremiah
Author-email: Garreth Jeremiah <twistedroutes76@example.com>
License: Apache-2.0
Project-URL: Homepage, https://github.com/twistedroutes/eg4_inverter_api
Project-URL: Repository, https://github.com/twistedroutes/eg4_inverter_api
Project-URL: Issues, https://github.com/twistedroutes/eg4_inverter_api/issues
Keywords: EG4,Inverter,API,Energy,Battery
Requires-Python: >=3.8
License-File: LICENSE
Requires-Dist: aiohttp>=3.8.1
Provides-Extra: dev
Requires-Dist: pytest>=7.0; extra == "dev"
Requires-Dist: pytest-asyncio>=0.20; extra == "dev"
Requires-Dist: python-dotenv>=1.0.0; extra == "dev"
Dynamic: author
Dynamic: home-page
Dynamic: requires-python
